WordCreator/__init__.py
WordCreator/word_creator.py
kvv_WordCreator-0.0.2.dist-info/LICENSE
kvv_WordCreator-0.0.2.dist-info/METADATA
kvv_WordCreator-0.0.2.dist-info/WHEEL
kvv_WordCreator-0.0.2.dist-info/top_level.txt
kvv_WordCreator-0.0.2.dist-info/RECORD
