Metadata-Version: 2.1
Name: kvv-WordCreator
Version: 0.0.2
Summary: WordCreator is a helper package to create Word spreadsheets out of Publications
Home-page: https://github.com/VladKornilov/WordCreator
Author: Vladislav Kornilov
Author-email: v.kornilovv@yandex.ru
Project-URL: Bug Tracker, https://github.com/VladKornilov/WordCreator/issues
Classifier: Programming Language :: Python :: 3
Classifier: License :: OSI Approved :: Apache Software License
Classifier: Operating System :: OS Independent
Requires-Python: >=3.6
License-File: LICENSE
Requires-Dist: python-docx
Requires-Dist: kvv-StoredObjects
